djangorestframework_oauth-1.1.0.dist-info/DESCRIPTION.rst
djangorestframework_oauth-1.1.0.dist-info/METADATA
djangorestframework_oauth-1.1.0.dist-info/metadata.json
djangorestframework_oauth-1.1.0.dist-info/RECORD
djangorestframework_oauth-1.1.0.dist-info/top_level.txt
djangorestframework_oauth-1.1.0.dist-info/WHEEL
rest_framework_oauth/__init__.py
rest_framework_oauth/authentication.py
rest_framework_oauth/compat.py
rest_framework_oauth/permissions.py
