Metadata-Version: 1.1
Name: djangorestframework-oauth
Version: 1.1.0
Summary: OAuth support for Django REST Framework
Home-page: https://github.com/jpadilla/django-rest-framework-oauth
Author: José Padilla
Author-email: hello@jpadilla.com
License: BSD
Platform: UNKNOWN
Classifier: Development Status :: 5 - Production/Stable
Classifier: Environment :: Web Environment
Classifier: Framework :: Django
Classifier: Intended Audience :: Developers
Classifier: License :: OSI Approved :: BSD License
Classifier: Operating System :: OS Independent
Classifier: Natural Language :: English
Classifier: Programming Language :: Python :: 2
Classifier: Programming Language :: Python :: 2.7
Classifier: Topic :: Internet :: WWW/HTTP
